{
  "id": 115,
  "tmdb": 451945,
  "title": "BPM (Beats per Minute)",
  "original_title": "120 battements par minute",
  "image": "https://image.tmdb.org/t/p/original/azLtGx5ZhdTSP2b4oNLWtiE51OW.jpg",
  "language": "fr",
  "release_date": "2017-08-23",
  "rating": 7.717,
  "reviews": [
    {
      "review_date": "2020-06-07",
      "rating": 7.717,
      "scores": {
        "firstImpression": 8,
        "overallFeeling": 8,
        "story": 8,
        "character": 8,
        "director": 8,
        "performance": 8,
        "visual": 8,
        "art": 7,
        "editing": 8,
        "sound": 8,
        "music": 8
      }
    }
  ]
}