{
  "id": 193,
  "tmdb": 1701,
  "title": "Con Air",
  "original_title": "Con Air",
  "image": "https://image.tmdb.org/t/p/original/kOKjgrEzGOP92rVQ6srA9jtp60l.jpg",
  "language": "en",
  "release_date": "1997-06-05",
  "rating": 6.674,
  "reviews": [
    {
      "review_date": "2021-01-16",
      "rating": 6.674,
      "scores": {
        "firstImpression": 7,
        "review": 6,
        "story": 6,
        "character": 7,
        "directing": 8,
        "acting": 7,
        "picture": 7,
        "art": 8,
        "editing": 8,
        "sound": 8,
        "music": 8
      }
    }
  ]
}
