{
  "id": 314,
  "tmdb": 592863,
  "title": "Respect",
  "original_title": "Respect",
  "image": "https://image.tmdb.org/t/p/original/iUtPwOBZJc8uJnDqlCXTibdgxKz.jpg",
  "language": "en",
  "release_date": "2021-08-12",
  "rating": 6.135,
  "reviews": [
    {
      "review_date": "2021-08-13",
      "rating": 6.135,
      "scores": {
        "firstImpression": 6,
        "overallFeeling": 5,
        "story": 6,
        "character": 7,
        "director": 7,
        "performance": 6,
        "visual": 7,
        "art": 7,
        "editing": 7,
        "sound": 7,
        "music": 8
      }
    }
  ]
}