{
  "id": 343,
  "tmdb": 567690,
  "title": "Dear Evan Hansen",
  "original_title": "Dear Evan Hansen",
  "image": "https://image.tmdb.org/t/p/original/hKjBQhsnCMt86kPKpPwV4meeFPo.jpg",
  "language": "en",
  "release_date": "2021-09-24",
  "rating": 4.12,
  "reviews": [
    {
      "review_date": "2021-09-26",
      "rating": 4.12,
      "scores": {
        "firstImpression": 4,
        "overallFeeling": 4,
        "story": 4,
        "character": 4,
        "director": 3,
        "performance": 6,
        "visual": 6,
        "art": 6,
        "editing": 7,
        "sound": 7,
        "music": 8
      }
    }
  ]
}