{
  "id": 445,
  "tmdb": 751237,
  "title": "Umma",
  "original_title": "Umma",
  "image": "https://image.tmdb.org/t/p/original/moLnqJmZ00i2opS0bzCVcaGC0iI.jpg",
  "language": "en",
  "release_date": "2022-03-18",
  "rating": 4.916,
  "reviews": [
    {
      "review_date": "2022-03-17",
      "rating": 4.916,
      "scores": {
        "firstImpression": 4,
        "review": 3,
        "story": 5,
        "character": 6,
        "directing": 5,
        "acting": 6,
        "picture": 7,
        "art": 7,
        "editing": 7,
        "sound": 7,
        "music": 5
      }
    }
  ]
}
