{
  "id": 76,
  "tmdb": 512788,
  "title": "Crystal Sky of Yesterday",
  "original_title": "昨日青空",
  "image": "https://image.tmdb.org/t/p/original/bBGlQXZ0ot3IrlnBANeRgnpK2NZ.jpg",
  "language": "zh",
  "release_date": "2018-07-21",
  "rating": 6.828,
  "reviews": [
    {
      "review_date": "2020-02-05",
      "rating": 6.828,
      "scores": {
        "firstImpression": 6,
        "review": 6,
        "story": 7,
        "character": 7,
        "directing": 6,
        "acting": 7,
        "picture": 9,
        "art": 9,
        "editing": 7,
        "sound": 7,
        "music": 10
      }
    }
  ]
}
