{
  "id": 86,
  "tmdb": 769,
  "title": "GoodFellas",
  "original_title": "GoodFellas",
  "image": "https://image.tmdb.org/t/p/original/aKuFiU82s5ISJpGZp7YkIr3kCUd.jpg",
  "language": "en",
  "release_date": "1990-09-12",
  "rating": 8.631,
  "reviews": [
    {
      "review_date": "2020-03-02",
      "rating": 8.631,
      "scores": {
        "firstImpression": 9,
        "overallFeeling": 9,
        "story": 9,
        "character": 8,
        "director": 9,
        "performance": 9,
        "visual": 9,
        "art": 9,
        "editing": 9,
        "sound": 9,
        "music": 8
      }
    }
  ]
}